bitgauss-0.3.4.dist-info/METADATA
bitgauss-0.3.4.dist-info/WHEEL
bitgauss.libs/libgcc_s-b5472b99.so.1
bitgauss/__init__.py
bitgauss/__init__.pyi
bitgauss/bitgauss.cpython-313t-i386-linux-musl.so
bitgauss/py.typed
bitgauss-0.3.4.dist-info/RECORD
