Metadata-Version: 2.4
Name: bitgauss
Version: 0.3.4
Classifier: Environment :: Console
Classifier: Programming Language :: Python :: 3.9
Classifier: Programming Language :: Python :: 3.10
Classifier: Programming Language :: Python :: 3.11
Classifier: Programming Language :: Python :: 3.12
Classifier: Programming Language :: Python :: 3.13
Classifier: License :: OSI Approved :: Apache Software License
Classifier: Operating System :: MacOS :: MacOS X
Classifier: Operating System :: POSIX :: Linux
Classifier: Operating System :: Microsoft :: Windows
Classifier: Intended Audience :: Developers
Classifier: Intended Audience :: Science/Research
Classifier: Topic :: Scientific/Engineering
Requires-Dist: pytest>=8.4.1 ; extra == 'test'
Provides-Extra: test
Summary: A fast boolean linear algebra library
Home-Page: https://github.com/akissinger/bitgauss
Author: Aleks Kissinger <aleks0@gmail.com>
Author-email: Aleks Kissinger <aleks0@gmail.com>
Maintainer-email: Aleks Kissinger <aleks0@gmail.com>
License: Apache-2.0
Requires-Python: >=3.9
Project-URL: homepage, https://github.com/akissinger/bitgauss
Project-URL: repository, https://github.com/akissinger/bitgauss
